{
  "id": "LYD_Warehouse_All_3",
  "asset_path": "/Game/WorldGeneration/Layouts/Warehouse/All/LYD_Warehouse_All_3",
  "class": "ULayoutDefinition",
  "parent_classes": [
    "UWorldGenObjectDefinition",
    "UDataAsset",
    "UObject"
  ],
  "properties": {
    "layout_objects": {
      "type": "array",
      "element_type": {
        "type": "struct",
        "struct_name": "LayoutObject",
        "fields": {
          "layout_actor_type": {
            "type": "enum",
            "enum_name": "LayoutActorType"
          },
          "b_visual_helper": {
            "type": "bool"
          },
          "definition_filter": {
            "type": "struct",
            "struct_name": "DefinitionFilter",
            "fields": {
              "seed_offset": {
                "type": "int"
              },
              "search_queries": {
                "type": "array",
                "element_type": {
                  "type": "struct",
                  "struct_name": "ProxySearchTreeQuery",
                  "fields": {
                    "search_query": {
                      "type": "enum",
                      "enum_name": "SearchQuery"
                    },
                    "tags": {
                      "type": "gameplay_tag_container"
                    },
                    "b_not": {
                      "type": "bool"
                    }
                  }
                }
              },
              "tile_requirements": {
                "type": "array",
                "element_type": null
              },
              "spawn_chance_over": {
                "type": "float"
              },
              "spawn_chance_under": {
                "type": "float"
              }
            }
          },
          "transform": {
            "type": "struct",
            "struct_name": "Transform",
            "fields": {
              "rotation": {
                "type": "struct",
                "struct_name": "Quat",
                "fields": {
                  "x": {
                    "type": "float"
                  },
                  "y": {
                    "type": "float"
                  },
                  "z": {
                    "type": "float"
                  },
                  "w": {
                    "type": "float"
                  }
                }
              },
              "translation": {
                "type": "struct",
                "struct_name": "Vector",
                "fields": {
                  "x": {
                    "type": "float"
                  },
                  "y": {
                    "type": "float"
                  },
                  "z": {
                    "type": "float"
                  }
                }
              },
              "scale3_d": {
                "type": "struct",
                "struct_name": "Vector",
                "fields": {
                  "x": {
                    "type": "float"
                  },
                  "y": {
                    "type": "float"
                  },
                  "z": {
                    "type": "float"
                  }
                }
              }
            }
          }
        }
      },
      "value": [
        {
          "type": "struct",
          "struct_name": "LayoutObject",
          "value": {
            "layout_actor_type": {
              "type": "enum",
              "enum_name": "LayoutActorType",
              "value": "<LayoutActorType.LAYOUT: 1>"
            },
            "b_visual_helper": {
              "type": "bool",
              "value": false
            },
            "definition_filter": {
              "type": "struct",
              "struct_name": "DefinitionFilter",
              "value": {
                "seed_offset": {
                  "type": "int",
                  "value": -1
                },
                "search_queries": {
                  "type": "array",
                  "element_type": {
                    "type": "struct",
                    "struct_name": "ProxySearchTreeQuery",
                    "fields": {
                      "search_query": {
                        "type": "enum",
                        "enum_name": "SearchQuery"
                      },
                      "tags": {
                        "type": "gameplay_tag_container"
                      },
                      "b_not": {
                        "type": "bool"
                      }
                    }
                  },
                  "value": [
                    {
                      "type": "struct",
                      "struct_name": "ProxySearchTreeQuery",
                      "value": {
                        "search_query": {
                          "type": "enum",
                          "enum_name": "SearchQuery",
                          "value": "<SearchQuery.HAS_ALL_EXACT: 4>"
                        },
                        "tags": {
                          "type": "gameplay_tag_container",
                          "value": [
                            "Layout.Type.Rack",
                            "Tile.Biome.Warehouse"
                          ]
                        },
                        "b_not": {
                          "type": "bool",
                          "value": false
                        }
                      }
                    }
                  ]
                },
                "tile_requirements": {
                  "type": "array",
                  "element_type": null,
                  "value": []
                },
                "spawn_chance_over": {
                  "type": "float",
                  "value": 0.0
                },
                "spawn_chance_under": {
                  "type": "float",
                  "value": 1.0
                }
              }
            },
            "transform": {
              "type": "struct",
              "struct_name": "Transform",
              "value": {
                "rotation": {
                  "type": "struct",
                  "struct_name": "Quat",
                  "value": {
                    "x": {
                      "type": "float",
                      "value": 0.0
                    },
                    "y": {
                      "type": "float",
                      "value": 0.0
                    },
                    "z": {
                      "type": "float",
                      "value": 0.0
                    },
                    "w": {
                      "type": "float",
                      "value": 1.0
                    }
                  }
                },
                "translation": {
                  "type": "struct",
                  "struct_name": "Vector",
                  "value": {
                    "x": {
                      "type": "float",
                      "value": 667.9087743817962
                    },
                    "y": {
                      "type": "float",
                      "value": 403.19413979325367
                    },
                    "z": {
                      "type": "float",
                      "value": -1.3895294159738114e-07
                    }
                  }
                },
                "scale3_d": {
                  "type": "struct",
                  "struct_name": "Vector",
                  "value": {
                    "x": {
                      "type": "float",
                      "value": 1.0
                    },
                    "y": {
                      "type": "float",
                      "value": 1.0
                    },
                    "z": {
                      "type": "float",
                      "value": 1.0
                    }
                  }
                }
              }
            }
          }
        },
        {
          "type": "struct",
          "struct_name": "LayoutObject",
          "value": {
            "layout_actor_type": {
              "type": "enum",
              "enum_name": "LayoutActorType",
              "value": "<LayoutActorType.LAYOUT: 1>"
            },
            "b_visual_helper": {
              "type": "bool",
              "value": false
            },
            "definition_filter": {
              "type": "struct",
              "struct_name": "DefinitionFilter",
              "value": {
                "seed_offset": {
                  "type": "int",
                  "value": -1
                },
                "search_queries": {
                  "type": "array",
                  "element_type": {
                    "type": "struct",
                    "struct_name": "ProxySearchTreeQuery",
                    "fields": {
                      "search_query": {
                        "type": "enum",
                        "enum_name": "SearchQuery"
                      },
                      "tags": {
                        "type": "gameplay_tag_container"
                      },
                      "b_not": {
                        "type": "bool"
                      }
                    }
                  },
                  "value": [
                    {
                      "type": "struct",
                      "struct_name": "ProxySearchTreeQuery",
                      "value": {
                        "search_query": {
                          "type": "enum",
                          "enum_name": "SearchQuery",
                          "value": "<SearchQuery.HAS_ALL_EXACT: 4>"
                        },
                        "tags": {
                          "type": "gameplay_tag_container",
                          "value": [
                            "Layout.Type.Rack",
                            "Tile.Biome.Warehouse"
                          ]
                        },
                        "b_not": {
                          "type": "bool",
                          "value": false
                        }
                      }
                    }
                  ]
                },
                "tile_requirements": {
                  "type": "array",
                  "element_type": null,
                  "value": []
                },
                "spawn_chance_over": {
                  "type": "float",
                  "value": 0.0
                },
                "spawn_chance_under": {
                  "type": "float",
                  "value": 1.0
                }
              }
            },
            "transform": {
              "type": "struct",
              "struct_name": "Transform",
              "value": {
                "rotation": {
                  "type": "struct",
                  "struct_name": "Quat",
                  "value": {
                    "x": {
                      "type": "float",
                      "value": 0.0
                    },
                    "y": {
                      "type": "float",
                      "value": -0.0
                    },
                    "z": {
                      "type": "float",
                      "value": 0.707106776884522
                    },
                    "w": {
                      "type": "float",
                      "value": 0.7071067854885732
                    }
                  }
                },
                "translation": {
                  "type": "struct",
                  "struct_name": "Vector",
                  "value": {
                    "x": {
                      "type": "float",
                      "value": 424.43338644635116
                    },
                    "y": {
                      "type": "float",
                      "value": 669.5039326855504
                    },
                    "z": {
                      "type": "float",
                      "value": 6.257924951569294e-07
                    }
                  }
                },
                "scale3_d": {
                  "type": "struct",
                  "struct_name": "Vector",
                  "value": {
                    "x": {
                      "type": "float",
                      "value": 1.0
                    },
                    "y": {
                      "type": "float",
                      "value": 1.0
                    },
                    "z": {
                      "type": "float",
                      "value": 1.0
                    }
                  }
                }
              }
            }
          }
        },
        {
          "type": "struct",
          "struct_name": "LayoutObject",
          "value": {
            "layout_actor_type": {
              "type": "enum",
              "enum_name": "LayoutActorType",
              "value": "<LayoutActorType.LAYOUT: 1>"
            },
            "b_visual_helper": {
              "type": "bool",
              "value": false
            },
            "definition_filter": {
              "type": "struct",
              "struct_name": "DefinitionFilter",
              "value": {
                "seed_offset": {
                  "type": "int",
                  "value": -1
                },
                "search_queries": {
                  "type": "array",
                  "element_type": {
                    "type": "struct",
                    "struct_name": "ProxySearchTreeQuery",
                    "fields": {
                      "search_query": {
                        "type": "enum",
                        "enum_name": "SearchQuery"
                      },
                      "tags": {
                        "type": "gameplay_tag_container"
                      },
                      "b_not": {
                        "type": "bool"
                      }
                    }
                  },
                  "value": [
                    {
                      "type": "struct",
                      "struct_name": "ProxySearchTreeQuery",
                      "value": {
                        "search_query": {
                          "type": "enum",
                          "enum_name": "SearchQuery",
                          "value": "<SearchQuery.HAS_ALL_EXACT: 4>"
                        },
                        "tags": {
                          "type": "gameplay_tag_container",
                          "value": [
                            "Layout.Type.Rack",
                            "Tile.Biome.Warehouse"
                          ]
                        },
                        "b_not": {
                          "type": "bool",
                          "value": false
                        }
                      }
                    }
                  ]
                },
                "tile_requirements": {
                  "type": "array",
                  "element_type": null,
                  "value": []
                },
                "spawn_chance_over": {
                  "type": "float",
                  "value": 0.0
                },
                "spawn_chance_under": {
                  "type": "float",
                  "value": 1.0
                }
              }
            },
            "transform": {
              "type": "struct",
              "struct_name": "Transform",
              "value": {
                "rotation": {
                  "type": "struct",
                  "struct_name": "Quat",
                  "value": {
                    "x": {
                      "type": "float",
                      "value": 0.0
                    },
                    "y": {
                      "type": "float",
                      "value": -0.0
                    },
                    "z": {
                      "type": "float",
                      "value": 0.7071067750158768
                    },
                    "w": {
                      "type": "float",
                      "value": 0.7071067873572183
                    }
                  }
                },
                "translation": {
                  "type": "struct",
                  "struct_name": "Vector",
                  "value": {
                    "x": {
                      "type": "float",
                      "value": 424.4333563749527
                    },
                    "y": {
                      "type": "float",
                      "value": -680.1597370374814
                    },
                    "z": {
                      "type": "float",
                      "value": 9.999936310123303e-07
                    }
                  }
                },
                "scale3_d": {
                  "type": "struct",
                  "struct_name": "Vector",
                  "value": {
                    "x": {
                      "type": "float",
                      "value": 1.0
                    },
                    "y": {
                      "type": "float",
                      "value": 1.0
                    },
                    "z": {
                      "type": "float",
                      "value": 1.0
                    }
                  }
                }
              }
            }
          }
        },
        {
          "type": "struct",
          "struct_name": "LayoutObject",
          "value": {
            "layout_actor_type": {
              "type": "enum",
              "enum_name": "LayoutActorType",
              "value": "<LayoutActorType.LAYOUT: 1>"
            },
            "b_visual_helper": {
              "type": "bool",
              "value": false
            },
            "definition_filter": {
              "type": "struct",
              "struct_name": "DefinitionFilter",
              "value": {
                "seed_offset": {
                  "type": "int",
                  "value": -1
                },
                "search_queries": {
                  "type": "array",
                  "element_type": {
                    "type": "struct",
                    "struct_name": "ProxySearchTreeQuery",
                    "fields": {
                      "search_query": {
                        "type": "enum",
                        "enum_name": "SearchQuery"
                      },
                      "tags": {
                        "type": "gameplay_tag_container"
                      },
                      "b_not": {
                        "type": "bool"
                      }
                    }
                  },
                  "value": [
                    {
                      "type": "struct",
                      "struct_name": "ProxySearchTreeQuery",
                      "value": {
                        "search_query": {
                          "type": "enum",
                          "enum_name": "SearchQuery",
                          "value": "<SearchQuery.HAS_ALL_EXACT: 4>"
                        },
                        "tags": {
                          "type": "gameplay_tag_container",
                          "value": [
                            "Layout.Type.Rack",
                            "Tile.Biome.Warehouse"
                          ]
                        },
                        "b_not": {
                          "type": "bool",
                          "value": false
                        }
                      }
                    }
                  ]
                },
                "tile_requirements": {
                  "type": "array",
                  "element_type": null,
                  "value": []
                },
                "spawn_chance_over": {
                  "type": "float",
                  "value": 0.0
                },
                "spawn_chance_under": {
                  "type": "float",
                  "value": 1.0
                }
              }
            },
            "transform": {
              "type": "struct",
              "struct_name": "Transform",
              "value": {
                "rotation": {
                  "type": "struct",
                  "struct_name": "Quat",
                  "value": {
                    "x": {
                      "type": "float",
                      "value": 0.0
                    },
                    "y": {
                      "type": "float",
                      "value": 0.0
                    },
                    "z": {
                      "type": "float",
                      "value": 0.0
                    },
                    "w": {
                      "type": "float",
                      "value": 1.0
                    }
                  }
                },
                "translation": {
                  "type": "struct",
                  "struct_name": "Vector",
                  "value": {
                    "x": {
                      "type": "float",
                      "value": 668.8220006079429
                    },
                    "y": {
                      "type": "float",
                      "value": -409.0871597313241
                    },
                    "z": {
                      "type": "float",
                      "value": 8.547237939637853e-08
                    }
                  }
                },
                "scale3_d": {
                  "type": "struct",
                  "struct_name": "Vector",
                  "value": {
                    "x": {
                      "type": "float",
                      "value": 1.0
                    },
                    "y": {
                      "type": "float",
                      "value": 1.0
                    },
                    "z": {
                      "type": "float",
                      "value": 1.0
                    }
                  }
                }
              }
            }
          }
        },
        {
          "type": "struct",
          "struct_name": "LayoutObject",
          "value": {
            "layout_actor_type": {
              "type": "enum",
              "enum_name": "LayoutActorType",
              "value": "<LayoutActorType.LAYOUT: 1>"
            },
            "b_visual_helper": {
              "type": "bool",
              "value": false
            },
            "definition_filter": {
              "type": "struct",
              "struct_name": "DefinitionFilter",
              "value": {
                "seed_offset": {
                  "type": "int",
                  "value": -1
                },
                "search_queries": {
                  "type": "array",
                  "element_type": {
                    "type": "struct",
                    "struct_name": "ProxySearchTreeQuery",
                    "fields": {
                      "search_query": {
                        "type": "enum",
                        "enum_name": "SearchQuery"
                      },
                      "tags": {
                        "type": "gameplay_tag_container"
                      },
                      "b_not": {
                        "type": "bool"
                      }
                    }
                  },
                  "value": [
                    {
                      "type": "struct",
                      "struct_name": "ProxySearchTreeQuery",
                      "value": {
                        "search_query": {
                          "type": "enum",
                          "enum_name": "SearchQuery",
                          "value": "<SearchQuery.HAS_ALL_EXACT: 4>"
                        },
                        "tags": {
                          "type": "gameplay_tag_container",
                          "value": [
                            "Layout.Type.Rack",
                            "Tile.Biome.Warehouse"
                          ]
                        },
                        "b_not": {
                          "type": "bool",
                          "value": false
                        }
                      }
                    }
                  ]
                },
                "tile_requirements": {
                  "type": "array",
                  "element_type": null,
                  "value": []
                },
                "spawn_chance_over": {
                  "type": "float",
                  "value": 0.0
                },
                "spawn_chance_under": {
                  "type": "float",
                  "value": 1.0
                }
              }
            },
            "transform": {
              "type": "struct",
              "struct_name": "Transform",
              "value": {
                "rotation": {
                  "type": "struct",
                  "struct_name": "Quat",
                  "value": {
                    "x": {
                      "type": "float",
                      "value": 0.0
                    },
                    "y": {
                      "type": "float",
                      "value": -0.0
                    },
                    "z": {
                      "type": "float",
                      "value": 0.9999999999999999
                    },
                    "w": {
                      "type": "float",
                      "value": 1.2167965141200097e-08
                    }
                  }
                },
                "translation": {
                  "type": "struct",
                  "struct_name": "Vector",
                  "value": {
                    "x": {
                      "type": "float",
                      "value": -668.7040118755008
                    },
                    "y": {
                      "type": "float",
                      "value": -400.21901506661345
                    },
                    "z": {
                      "type": "float",
                      "value": -2.2737367544323206e-13
                    }
                  }
                },
                "scale3_d": {
                  "type": "struct",
                  "struct_name": "Vector",
                  "value": {
                    "x": {
                      "type": "float",
                      "value": 1.0
                    },
                    "y": {
                      "type": "float",
                      "value": 1.0
                    },
                    "z": {
                      "type": "float",
                      "value": 1.0
                    }
                  }
                }
              }
            }
          }
        },
        {
          "type": "struct",
          "struct_name": "LayoutObject",
          "value": {
            "layout_actor_type": {
              "type": "enum",
              "enum_name": "LayoutActorType",
              "value": "<LayoutActorType.LAYOUT: 1>"
            },
            "b_visual_helper": {
              "type": "bool",
              "value": false
            },
            "definition_filter": {
              "type": "struct",
              "struct_name": "DefinitionFilter",
              "value": {
                "seed_offset": {
                  "type": "int",
                  "value": -1
                },
                "search_queries": {
                  "type": "array",
                  "element_type": {
                    "type": "struct",
                    "struct_name": "ProxySearchTreeQuery",
                    "fields": {
                      "search_query": {
                        "type": "enum",
                        "enum_name": "SearchQuery"
                      },
                      "tags": {
                        "type": "gameplay_tag_container"
                      },
                      "b_not": {
                        "type": "bool"
                      }
                    }
                  },
                  "value": [
                    {
                      "type": "struct",
                      "struct_name": "ProxySearchTreeQuery",
                      "value": {
                        "search_query": {
                          "type": "enum",
                          "enum_name": "SearchQuery",
                          "value": "<SearchQuery.HAS_ALL_EXACT: 4>"
                        },
                        "tags": {
                          "type": "gameplay_tag_container",
                          "value": [
                            "Layout.Type.Rack",
                            "Tile.Biome.Warehouse"
                          ]
                        },
                        "b_not": {
                          "type": "bool",
                          "value": false
                        }
                      }
                    }
                  ]
                },
                "tile_requirements": {
                  "type": "array",
                  "element_type": null,
                  "value": []
                },
                "spawn_chance_over": {
                  "type": "float",
                  "value": 0.0
                },
                "spawn_chance_under": {
                  "type": "float",
                  "value": 1.0
                }
              }
            },
            "transform": {
              "type": "struct",
              "struct_name": "Transform",
              "value": {
                "rotation": {
                  "type": "struct",
                  "struct_name": "Quat",
                  "value": {
                    "x": {
                      "type": "float",
                      "value": -0.0
                    },
                    "y": {
                      "type": "float",
                      "value": 0.0
                    },
                    "z": {
                      "type": "float",
                      "value": -0.7071067959612675
                    },
                    "w": {
                      "type": "float",
                      "value": 0.7071067664118275
                    }
                  }
                },
                "translation": {
                  "type": "struct",
                  "struct_name": "Vector",
                  "value": {
                    "x": {
                      "type": "float",
                      "value": -425.22863683729423
                    },
                    "y": {
                      "type": "float",
                      "value": -666.5288199170113
                    },
                    "z": {
                      "type": "float",
                      "value": 9.999997726263245e-07
                    }
                  }
                },
                "scale3_d": {
                  "type": "struct",
                  "struct_name": "Vector",
                  "value": {
                    "x": {
                      "type": "float",
                      "value": 1.0
                    },
                    "y": {
                      "type": "float",
                      "value": 1.0
                    },
                    "z": {
                      "type": "float",
                      "value": 1.0
                    }
                  }
                }
              }
            }
          }
        },
        {
          "type": "struct",
          "struct_name": "LayoutObject",
          "value": {
            "layout_actor_type": {
              "type": "enum",
              "enum_name": "LayoutActorType",
              "value": "<LayoutActorType.LAYOUT: 1>"
            },
            "b_visual_helper": {
              "type": "bool",
              "value": false
            },
            "definition_filter": {
              "type": "struct",
              "struct_name": "DefinitionFilter",
              "value": {
                "seed_offset": {
                  "type": "int",
                  "value": -1
                },
                "search_queries": {
                  "type": "array",
                  "element_type": {
                    "type": "struct",
                    "struct_name": "ProxySearchTreeQuery",
                    "fields": {
                      "search_query": {
                        "type": "enum",
                        "enum_name": "SearchQuery"
                      },
                      "tags": {
                        "type": "gameplay_tag_container"
                      },
                      "b_not": {
                        "type": "bool"
                      }
                    }
                  },
                  "value": [
                    {
                      "type": "struct",
                      "struct_name": "ProxySearchTreeQuery",
                      "value": {
                        "search_query": {
                          "type": "enum",
                          "enum_name": "SearchQuery",
                          "value": "<SearchQuery.HAS_ALL_EXACT: 4>"
                        },
                        "tags": {
                          "type": "gameplay_tag_container",
                          "value": [
                            "Layout.Type.Rack",
                            "Tile.Biome.Warehouse"
                          ]
                        },
                        "b_not": {
                          "type": "bool",
                          "value": false
                        }
                      }
                    }
                  ]
                },
                "tile_requirements": {
                  "type": "array",
                  "element_type": null,
                  "value": []
                },
                "spawn_chance_over": {
                  "type": "float",
                  "value": 0.0
                },
                "spawn_chance_under": {
                  "type": "float",
                  "value": 1.0
                }
              }
            },
            "transform": {
              "type": "struct",
              "struct_name": "Transform",
              "value": {
                "rotation": {
                  "type": "struct",
                  "struct_name": "Quat",
                  "value": {
                    "x": {
                      "type": "float",
                      "value": -0.0
                    },
                    "y": {
                      "type": "float",
                      "value": 0.0
                    },
                    "z": {
                      "type": "float",
                      "value": -0.7071067959612675
                    },
                    "w": {
                      "type": "float",
                      "value": 0.7071067664118275
                    }
                  }
                },
                "translation": {
                  "type": "struct",
                  "struct_name": "Vector",
                  "value": {
                    "x": {
                      "type": "float",
                      "value": -426.223455451301
                    },
                    "y": {
                      "type": "float",
                      "value": 683.134850082984
                    },
                    "z": {
                      "type": "float",
                      "value": 9.999997726263245e-07
                    }
                  }
                },
                "scale3_d": {
                  "type": "struct",
                  "struct_name": "Vector",
                  "value": {
                    "x": {
                      "type": "float",
                      "value": 1.0
                    },
                    "y": {
                      "type": "float",
                      "value": 1.0
                    },
                    "z": {
                      "type": "float",
                      "value": 1.0
                    }
                  }
                }
              }
            }
          }
        },
        {
          "type": "struct",
          "struct_name": "LayoutObject",
          "value": {
            "layout_actor_type": {
              "type": "enum",
              "enum_name": "LayoutActorType",
              "value": "<LayoutActorType.LAYOUT: 1>"
            },
            "b_visual_helper": {
              "type": "bool",
              "value": false
            },
            "definition_filter": {
              "type": "struct",
              "struct_name": "DefinitionFilter",
              "value": {
                "seed_offset": {
                  "type": "int",
                  "value": -1
                },
                "search_queries": {
                  "type": "array",
                  "element_type": {
                    "type": "struct",
                    "struct_name": "ProxySearchTreeQuery",
                    "fields": {
                      "search_query": {
                        "type": "enum",
                        "enum_name": "SearchQuery"
                      },
                      "tags": {
                        "type": "gameplay_tag_container"
                      },
                      "b_not": {
                        "type": "bool"
                      }
                    }
                  },
                  "value": [
                    {
                      "type": "struct",
                      "struct_name": "ProxySearchTreeQuery",
                      "value": {
                        "search_query": {
                          "type": "enum",
                          "enum_name": "SearchQuery",
                          "value": "<SearchQuery.HAS_ALL_EXACT: 4>"
                        },
                        "tags": {
                          "type": "gameplay_tag_container",
                          "value": [
                            "Layout.Type.Rack",
                            "Tile.Biome.Warehouse"
                          ]
                        },
                        "b_not": {
                          "type": "bool",
                          "value": false
                        }
                      }
                    }
                  ]
                },
                "tile_requirements": {
                  "type": "array",
                  "element_type": null,
                  "value": []
                },
                "spawn_chance_over": {
                  "type": "float",
                  "value": 0.0
                },
                "spawn_chance_under": {
                  "type": "float",
                  "value": 1.0
                }
              }
            },
            "transform": {
              "type": "struct",
              "struct_name": "Transform",
              "value": {
                "rotation": {
                  "type": "struct",
                  "struct_name": "Quat",
                  "value": {
                    "x": {
                      "type": "float",
                      "value": 0.0
                    },
                    "y": {
                      "type": "float",
                      "value": -0.0
                    },
                    "z": {
                      "type": "float",
                      "value": 0.9999999999999999
                    },
                    "w": {
                      "type": "float",
                      "value": 1.2167965141200097e-08
                    }
                  }
                },
                "translation": {
                  "type": "struct",
                  "struct_name": "Vector",
                  "value": {
                    "x": {
                      "type": "float",
                      "value": -670.6121126449053
                    },
                    "y": {
                      "type": "float",
                      "value": 412.06228497783343
                    },
                    "z": {
                      "type": "float",
                      "value": -2.2737367544323206e-13
                    }
                  }
                },
                "scale3_d": {
                  "type": "struct",
                  "struct_name": "Vector",
                  "value": {
                    "x": {
                      "type": "float",
                      "value": 1.0
                    },
                    "y": {
                      "type": "float",
                      "value": 1.0
                    },
                    "z": {
                      "type": "float",
                      "value": 1.0
                    }
                  }
                }
              }
            }
          }
        },
        {
          "type": "struct",
          "struct_name": "LayoutObject",
          "value": {
            "layout_actor_type": {
              "type": "enum",
              "enum_name": "LayoutActorType",
              "value": "<LayoutActorType.LAYOUT: 1>"
            },
            "b_visual_helper": {
              "type": "bool",
              "value": false
            },
            "definition_filter": {
              "type": "struct",
              "struct_name": "DefinitionFilter",
              "value": {
                "seed_offset": {
                  "type": "int",
                  "value": -1
                },
                "search_queries": {
                  "type": "array",
                  "element_type": null,
                  "value": []
                },
                "tile_requirements": {
                  "type": "array",
                  "element_type": null,
                  "value": []
                },
                "spawn_chance_over": {
                  "type": "float",
                  "value": 0.0
                },
                "spawn_chance_under": {
                  "type": "float",
                  "value": 1.0
                }
              }
            },
            "layout_definition": {
              "type": "definition_ref",
              "class": "LayoutDefinition",
              "value": "LYD_Warehouse_Checkout"
            },
            "transform": {
              "type": "struct",
              "struct_name": "Transform",
              "value": {
                "rotation": {
                  "type": "struct",
                  "struct_name": "Quat",
                  "value": {
                    "x": {
                      "type": "float",
                      "value": 0.0
                    },
                    "y": {
                      "type": "float",
                      "value": 0.0
                    },
                    "z": {
                      "type": "float",
                      "value": 0.0
                    },
                    "w": {
                      "type": "float",
                      "value": 1.0
                    }
                  }
                },
                "translation": {
                  "type": "struct",
                  "struct_name": "Vector",
                  "value": {
                    "x": {
                      "type": "float",
                      "value": -338.0626137009888
                    },
                    "y": {
                      "type": "float",
                      "value": 444.1670659245143
                    },
                    "z": {
                      "type": "float",
                      "value": -2.003316358743177e-06
                    }
                  }
                },
                "scale3_d": {
                  "type": "struct",
                  "struct_name": "Vector",
                  "value": {
                    "x": {
                      "type": "float",
                      "value": 1.0
                    },
                    "y": {
                      "type": "float",
                      "value": 1.0
                    },
                    "z": {
                      "type": "float",
                      "value": 1.0
                    }
                  }
                }
              }
            }
          }
        },
        {
          "type": "struct",
          "struct_name": "LayoutObject",
          "value": {
            "layout_actor_type": {
              "type": "enum",
              "enum_name": "LayoutActorType",
              "value": "<LayoutActorType.LAYOUT: 1>"
            },
            "b_visual_helper": {
              "type": "bool",
              "value": false
            },
            "definition_filter": {
              "type": "struct",
              "struct_name": "DefinitionFilter",
              "value": {
                "seed_offset": {
                  "type": "int",
                  "value": -1
                },
                "search_queries": {
                  "type": "array",
                  "element_type": null,
                  "value": []
                },
                "tile_requirements": {
                  "type": "array",
                  "element_type": null,
                  "value": []
                },
                "spawn_chance_over": {
                  "type": "float",
                  "value": 0.0
                },
                "spawn_chance_under": {
                  "type": "float",
                  "value": 1.0
                }
              }
            },
            "layout_definition": {
              "type": "definition_ref",
              "class": "LayoutDefinition",
              "value": "LYD_Warehouse_Checkout"
            },
            "transform": {
              "type": "struct",
              "struct_name": "Transform",
              "value": {
                "rotation": {
                  "type": "struct",
                  "struct_name": "Quat",
                  "value": {
                    "x": {
                      "type": "float",
                      "value": 0.0
                    },
                    "y": {
                      "type": "float",
                      "value": 0.0
                    },
                    "z": {
                      "type": "float",
                      "value": 0.0
                    },
                    "w": {
                      "type": "float",
                      "value": 1.0
                    }
                  }
                },
                "translation": {
                  "type": "struct",
                  "struct_name": "Vector",
                  "value": {
                    "x": {
                      "type": "float",
                      "value": -338.0626227607586
                    },
                    "y": {
                      "type": "float",
                      "value": -287.111271104941
                    },
                    "z": {
                      "type": "float",
                      "value": -1.999999886313162e-06
                    }
                  }
                },
                "scale3_d": {
                  "type": "struct",
                  "struct_name": "Vector",
                  "value": {
                    "x": {
                      "type": "float",
                      "value": 1.0
                    },
                    "y": {
                      "type": "float",
                      "value": 1.0
                    },
                    "z": {
                      "type": "float",
                      "value": 1.0
                    }
                  }
                }
              }
            }
          }
        },
        {
          "type": "struct",
          "struct_name": "LayoutObject",
          "value": {
            "layout_actor_type": {
              "type": "enum",
              "enum_name": "LayoutActorType",
              "value": "<LayoutActorType.ENEMY_SPAWN_POINT: 2>"
            },
            "b_visual_helper": {
              "type": "bool",
              "value": false
            },
            "definition_filter": {
              "type": "struct",
              "struct_name": "DefinitionFilter",
              "value": {
                "seed_offset": {
                  "type": "int",
                  "value": -1
                },
                "search_queries": {
                  "type": "array",
                  "element_type": null,
                  "value": []
                },
                "tile_requirements": {
                  "type": "array",
                  "element_type": null,
                  "value": []
                },
                "spawn_chance_over": {
                  "type": "float",
                  "value": 0.0
                },
                "spawn_chance_under": {
                  "type": "float",
                  "value": 1.0
                }
              }
            },
            "enemy_spawn_point_definition": {
              "type": "definition_ref",
              "class": "EnemySpawnPointDefinition",
              "value": "ESP_Warehouse"
            },
            "transform": {
              "type": "struct",
              "struct_name": "Transform",
              "value": {
                "rotation": {
                  "type": "struct",
                  "struct_name": "Quat",
                  "value": {
                    "x": {
                      "type": "float",
                      "value": 0.0
                    },
                    "y": {
                      "type": "float",
                      "value": 0.0
                    },
                    "z": {
                      "type": "float",
                      "value": 0.0
                    },
                    "w": {
                      "type": "float",
                      "value": 1.0
                    }
                  }
                },
                "translation": {
                  "type": "struct",
                  "struct_name": "Vector",
                  "value": {
                    "x": {
                      "type": "float",
                      "value": 29.212537
                    },
                    "y": {
                      "type": "float",
                      "value": 61.269126
                    },
                    "z": {
                      "type": "float",
                      "value": 9.9e-05
                    }
                  }
                },
                "scale3_d": {
                  "type": "struct",
                  "struct_name": "Vector",
                  "value": {
                    "x": {
                      "type": "float",
                      "value": 1.0
                    },
                    "y": {
                      "type": "float",
                      "value": 1.0
                    },
                    "z": {
                      "type": "float",
                      "value": 1.0
                    }
                  }
                }
              }
            }
          }
        },
        {
          "type": "struct",
          "struct_name": "LayoutObject",
          "value": {
            "layout_actor_type": {
              "type": "enum",
              "enum_name": "LayoutActorType",
              "value": "<LayoutActorType.LAYOUT: 1>"
            },
            "b_visual_helper": {
              "type": "bool",
              "value": false
            },
            "definition_filter": {
              "type": "struct",
              "struct_name": "DefinitionFilter",
              "value": {
                "seed_offset": {
                  "type": "int",
                  "value": -1
                },
                "search_queries": {
                  "type": "array",
                  "element_type": null,
                  "value": []
                },
                "tile_requirements": {
                  "type": "array",
                  "element_type": null,
                  "value": []
                },
                "spawn_chance_over": {
                  "type": "float",
                  "value": 0.0
                },
                "spawn_chance_under": {
                  "type": "float",
                  "value": 1.0
                }
              }
            },
            "layout_definition": {
              "type": "definition_ref",
              "class": "LayoutDefinition",
              "value": "LYD_TileBase"
            },
            "transform": {
              "type": "struct",
              "struct_name": "Transform",
              "value": {
                "rotation": {
                  "type": "struct",
                  "struct_name": "Quat",
                  "value": {
                    "x": {
                      "type": "float",
                      "value": 0.0
                    },
                    "y": {
                      "type": "float",
                      "value": 0.0
                    },
                    "z": {
                      "type": "float",
                      "value": 0.0
                    },
                    "w": {
                      "type": "float",
                      "value": 1.0
                    }
                  }
                },
                "translation": {
                  "type": "struct",
                  "struct_name": "Vector",
                  "value": {
                    "x": {
                      "type": "float",
                      "value": 0.0
                    },
                    "y": {
                      "type": "float",
                      "value": 0.0
                    },
                    "z": {
                      "type": "float",
                      "value": 0.0
                    }
                  }
                },
                "scale3_d": {
                  "type": "struct",
                  "struct_name": "Vector",
                  "value": {
                    "x": {
                      "type": "float",
                      "value": 1.0
                    },
                    "y": {
                      "type": "float",
                      "value": 1.0
                    },
                    "z": {
                      "type": "float",
                      "value": 1.0
                    }
                  }
                }
              }
            }
          }
        }
      ]
    },
    "weighted_chance": {
      "type": "int",
      "value": 150
    },
    "world_gen_priority": {
      "type": "int",
      "value": 1000
    },
    "gameplay_tags": {
      "type": "gameplay_tag_container",
      "value": [
        "Tile.Layer.Floor",
        "Tile.MazeDirection.All",
        "Tile.Biome.Warehouse",
        "Layout.Type.Tile"
      ]
    }
  }
}
